nextcord/ext/ipc/__init__.py
nextcord/ext/ipc/client.py
nextcord/ext/ipc/errors.py
nextcord/ext/ipc/server.py
nextcord_ext_ipc-2.2.1.dist-info/LICENSE
nextcord_ext_ipc-2.2.1.dist-info/METADATA
nextcord_ext_ipc-2.2.1.dist-info/WHEEL
nextcord_ext_ipc-2.2.1.dist-info/top_level.txt
nextcord_ext_ipc-2.2.1.dist-info/RECORD
